{
  "title": "repo.md",
  "kind": "raw",
  "body_text": "# GitHub 분석: facebookresearch/EUPE\n\n> - URL: https://github.com/facebookresearch/EUPE\n> - 분석일: 2026-04-07\n\n## 개요\n\n- **설명**: Efficient Universal Perception Encoder: a single on-device vision encoder with versatile representations that match or exceed specialized experts across multiple task domains.\n- **Stars**: ⭐ 351 | Forks: 16\n- **라이선스**: NOASSERTION\n- **주 언어**: Python\n\n## 실행 가능 상태: 모델 다운로드 스크립트 있음 (다운로드 후 실행 가능)\n\n| 항목 | 상태 |\n|------|------|\n| README | Y |\n| 소스 코드 (44개) | Y |\n| 의존성 파일 | Y |\n| 모델/체크포인트 | script |\n| Docker | N |\n\n## 파일 구조\n\n```\n.docstr.yaml\n.git/config\n.git/description\n.git/HEAD\n.git/index\n.git/packed-refs\n.git/shallow\n.gitignore\nassets/teaser.png\nCODE_OF_CONDUCT.md\nconda.yaml\nCONTRIBUTING.md\neupe/__init__.py\nhubconf.py\nLICENSE.md\npyproject.toml\nREADME.md\nrequirements.txt\nsetup.py\n```",
  "source_path": "data/research/daily/2026-04-07/papers/2603.22387/repo.md",
  "links": [],
  "body": "# GitHub 분석: facebookresearch/EUPE\n\n> - URL: https://github.com/facebookresearch/EUPE\n> - 분석일: 2026-04-07\n\n## 개요\n\n- **설명**: Efficient Universal Perception Encoder: a single on-device vision encoder with versatile representations that match or exceed specialized experts across multiple task domains.\n- **Stars**: ⭐ 351 | Forks: 16\n- **라이선스**: NOASSERTION\n- **주 언어**: Python\n\n## 실행 가능 상태: 모델 다운로드 스크립트 있음 (다운로드 후 실행 가능)\n\n| 항목 | 상태 |\n|------|------|\n| README | Y |\n| 소스 코드 (44개) | Y |\n| 의존성 파일 | Y |\n| 모델/체크포인트 | script |\n| Docker | N |\n\n## 파일 구조\n\n```\n.docstr.yaml\n.git/config\n.git/description\n.git/HEAD\n.git/index\n.git/packed-refs\n.git/shallow\n.gitignore\nassets/teaser.png\nCODE_OF_CONDUCT.md\nconda.yaml\nCONTRIBUTING.md\neupe/__init__.py\nhubconf.py\nLICENSE.md\npyproject.toml\nREADME.md\nrequirements.txt\nsetup.py\n```\n"
}
