{
  "title": "paper.md",
  "kind": "raw",
  "body_text": "# 논문 분석: 2604.04874\n\n> - arxiv: https://arxiv.org/abs/2604.04874\n> - papers.cool: https://papers.cool/arxiv/2604.04874\n> - 분석일: 2026-04-08\n\nFree-Range Gaussians: Non-Grid-Aligned Generative 3D Gaussian Reconstruction | Cool Papers - 몰입형 논문 탐색\n\n## 2604.04874\n\n총계: 1\n\n## \n#1\n\nFree-Range Gaussians: Non-Grid-Aligned Generative 3D Gaussian Reconstruction  \n[PDF5]  \n[Copy]  \n[Kimi2]  \n[REL]\n\n저자:  \nAhan Shabanov,  \nPeter Hedman,  \nEthan Weber,  \nZhengqin Li,  \nDenis Rozumny,  \nGael Le Lan,  \nNaina Dhingra,  \nLei Luo,  \nAndrea Vedaldi,  \nChristian Richardt,  \nAndrea Tagliasacchi,  \nBo Zhu,  \nNumair Khan\n\n우리는 최소 4장의 이미지로부터 픽셀 정렬도, 복셀 정렬도 되지 않은 3D Gaussians를 예측하는 다중 뷰 재구성 방법 Free-Range Gaussians를 제시한다. 이는 Gaussian 파라미터에 대한 flow matching을 통해 수행된다. 우리의 생성적 재구성 정식화는 모델이 비격자 정렬 3D 데이터로 감독될 수 있게 하며, 관측되지 않은 영역에서 그럴듯한 내용을 합성할 수 있도록 한다. 따라서 고도로 중복된 격자 정렬 Gaussians를 생성하고, 비관측 영역에서 구멍이나 흐릿한 조건부 평균 문제를 겪는 기존 방법보다 개선된다. 고품질 결과에 필요한 Gaussian 수를 처리하기 위해, 우리는 공간적으로 관련된 Gaussians를 공동 transformer 토큰으로 묶는 계층적 패칭 방식을 도입하여 구조를 유지하면서 시퀀스 길이를 절반으로 줄인다. 또한 학습 중 timestep-weighted rendering loss를, 추론 시에는 photometric gradient guidance와 classifier-free guidance를 제안하여 충실도를 향상시킨다. Objaverse와 Google Scanned Objects에서의 실험은, 특히 입력 뷰가 객체의 일부를 관측하지 못하는 경우에, 훨씬 적은 Gaussian을 사용하면서도 픽셀 및 복셀 정렬 방법보다 일관되게 더 나은 성능을 보임을 보여준다.\n\n주제:  \nComputer Vision and Pattern Recognition\n\n게시: 2026-04-06 17:24:18 UTC\n\nkexue.fm 제작 | kimi.ai 기반\n\n포함 OR:\n\n제외:\n\n검색\n\n필터\n\n강조 표시\n\n표시한 논문:\n\n#1  \nFree-Range Gaussians: Non-Grid-Aligned Generative 3D Gaussian Reconstruction\n\n내보내기\n\nMagic Token:\n\nKimi 언어:\n\n中文  \nEnglish\n\n설명 언어:\n\n中文  \nEnglish\n\n저장\n\n버그 신고? 이슈 제출? 다음을 방문하세요:\n\nGithub: https://github.com/bojone/papers.cool\n\n계속하기 전에 면책 조항을 읽어 주세요.\n\n더 흥미로운 기능은 kexue.fm 및 kimi.ai를 방문하세요.",
  "source_path": "data/research/daily/2026-04-08/papers/2604.04874/paper.md",
  "links": [],
  "body": "# 논문 분석: 2604.04874\n\n> - arxiv: https://arxiv.org/abs/2604.04874\n> - papers.cool: https://papers.cool/arxiv/2604.04874\n> - 분석일: 2026-04-08\n\nFree-Range Gaussians: Non-Grid-Aligned Generative 3D Gaussian Reconstruction | Cool Papers - 몰입형 논문 탐색\n\n## 2604.04874\n\n총계: 1\n\n## \n#1\n\nFree-Range Gaussians: Non-Grid-Aligned Generative 3D Gaussian Reconstruction  \n[PDF5]  \n[Copy]  \n[Kimi2]  \n[REL]\n\n저자:  \nAhan Shabanov,  \nPeter Hedman,  \nEthan Weber,  \nZhengqin Li,  \nDenis Rozumny,  \nGael Le Lan,  \nNaina Dhingra,  \nLei Luo,  \nAndrea Vedaldi,  \nChristian Richardt,  \nAndrea Tagliasacchi,  \nBo Zhu,  \nNumair Khan\n\n우리는 최소 4장의 이미지로부터 픽셀 정렬도, 복셀 정렬도 되지 않은 3D Gaussians를 예측하는 다중 뷰 재구성 방법 Free-Range Gaussians를 제시한다. 이는 Gaussian 파라미터에 대한 flow matching을 통해 수행된다. 우리의 생성적 재구성 정식화는 모델이 비격자 정렬 3D 데이터로 감독될 수 있게 하며, 관측되지 않은 영역에서 그럴듯한 내용을 합성할 수 있도록 한다. 따라서 고도로 중복된 격자 정렬 Gaussians를 생성하고, 비관측 영역에서 구멍이나 흐릿한 조건부 평균 문제를 겪는 기존 방법보다 개선된다. 고품질 결과에 필요한 Gaussian 수를 처리하기 위해, 우리는 공간적으로 관련된 Gaussians를 공동 transformer 토큰으로 묶는 계층적 패칭 방식을 도입하여 구조를 유지하면서 시퀀스 길이를 절반으로 줄인다. 또한 학습 중 timestep-weighted rendering loss를, 추론 시에는 photometric gradient guidance와 classifier-free guidance를 제안하여 충실도를 향상시킨다. Objaverse와 Google Scanned Objects에서의 실험은, 특히 입력 뷰가 객체의 일부를 관측하지 못하는 경우에, 훨씬 적은 Gaussian을 사용하면서도 픽셀 및 복셀 정렬 방법보다 일관되게 더 나은 성능을 보임을 보여준다.\n\n주제:  \nComputer Vision and Pattern Recognition\n\n게시: 2026-04-06 17:24:18 UTC\n\nkexue.fm 제작 | kimi.ai 기반\n\n포함 OR:\n\n제외:\n\n검색\n\n필터\n\n강조 표시\n\n표시한 논문:\n\n#1  \nFree-Range Gaussians: Non-Grid-Aligned Generative 3D Gaussian Reconstruction\n\n내보내기\n\nMagic Token:\n\nKimi 언어:\n\n中文  \nEnglish\n\n설명 언어:\n\n中文  \nEnglish\n\n저장\n\n버그 신고? 이슈 제출? 다음을 방문하세요:\n\nGithub: https://github.com/bojone/papers.cool\n\n계속하기 전에 면책 조항을 읽어 주세요.\n\n더 흥미로운 기능은 kexue.fm 및 kimi.ai를 방문하세요.\n"
}
